basic_calcs/__init__.py
basic_calcs-0.0.3.dist-info/licenses/LICENSE
basic_calcs-0.0.3.dist-info/METADATA
basic_calcs-0.0.3.dist-info/WHEEL
basic_calcs-0.0.3.dist-info/top_level.txt
basic_calcs-0.0.3.dist-info/RECORD
