Metadata-Version: 2.4
Name: basic_calcs
Version: 0.0.3
Summary: python library for basic calculations.
Author-email: Faakhar Habeeb <faakhar.hzb@gmail.com>
License-Expression: MIT
Project-URL: Homepage, https://github.com/faakharhzb/basic_calcs
Project-URL: Repository, https://github.com/faakharhzb/basic_calcs.git
Project-URL: Bug Tracker, https://github.com/faakharhzb/basic_calcs/issues
Keywords: math,add,subtract,multiply,divide
Classifier: Development Status :: 3 - Alpha
Classifier: Programming Language :: Python
Requires-Python: >=3
License-File: LICENSE
Dynamic: license-file
